image_editor/__init__.py
image_editor/drawing_img.py
image_editor/effects.py
image_editor/transformations.py
tests/__init__.py
tests/test_drawing_img.py
image_editor-0.1.dist-info/LICENSE
image_editor-0.1.dist-info/METADATA
image_editor-0.1.dist-info/WHEEL
image_editor-0.1.dist-info/top_level.txt
image_editor-0.1.dist-info/RECORD
