Metadata-Version: 2.1
Name: image-editor
Version: 0.1
Summary: A simple image editing library with drawing tools and effects
Author: Aiden Metcalfe
License-File: LICENSE
Requires-Dist: Pillow
